MANIFEST.in
README.md
extra-requirements.txt
requirements.txt
setup.py
test-requirements.txt
gsicrawler/VERSION
gsicrawler/__init__.py
gsicrawler/tasks.py
gsicrawler/utils.py
gsicrawler.egg-info/PKG-INFO
gsicrawler.egg-info/SOURCES.txt
gsicrawler.egg-info/dependency_links.txt
gsicrawler.egg-info/requires.txt
gsicrawler.egg-info/top_level.txt