Metadata-Version: 2.1
Name: gsicrawler
Version: 0.2.0
Summary: Scrapers and web interface.
Home-page: https://github.com/gsi-upm/gsicrawler
Author: J. Fernando Sanchez
Author-email: balkian@gmail.com
License: UNKNOWN
Download-URL: https://github.com/gsi-upm/gsicrawler/archive/0.2.0.tar.gz
Keywords: scraping
Platform: UNKNOWN
Classifier: Programming Language :: Python :: 3
Requires-Python: >3.3
